huaweicloudsdkidentitycenterportalapi/__init__.py
huaweicloudsdkidentitycenterportalapi/v1/__init__.py
huaweicloudsdkidentitycenterportalapi/v1/identitycenterportalapi_async_client.py
huaweicloudsdkidentitycenterportalapi/v1/identitycenterportalapi_client.py
huaweicloudsdkidentitycenterportalapi/v1/identitycenterportalapi_credentials.py
huaweicloudsdkidentitycenterportalapi/v1/model/__init__.py
huaweicloudsdkidentitycenterportalapi/v1/model/account_info.py
huaweicloudsdkidentitycenterportalapi/v1/model/agency_credentials.py
huaweicloudsdkidentitycenterportalapi/v1/model/agency_info.py
huaweicloudsdkidentitycenterportalapi/v1/model/get_agency_credentials_request.py
huaweicloudsdkidentitycenterportalapi/v1/model/get_agency_credentials_response.py
huaweicloudsdkidentitycenterportalapi/v1/model/list_account_agencies_request.py
huaweicloudsdkidentitycenterportalapi/v1/model/list_account_agencies_response.py
huaweicloudsdkidentitycenterportalapi/v1/model/list_accounts_request.py
huaweicloudsdkidentitycenterportalapi/v1/model/list_accounts_response.py
huaweicloudsdkidentitycenterportalapi/v1/model/logout_request.py
huaweicloudsdkidentitycenterportalapi/v1/model/logout_response.py
huaweicloudsdkidentitycenterportalapi/v1/model/page_info_dto.py
huaweicloudsdkidentitycenterportalapi/v1/region/__init__.py
huaweicloudsdkidentitycenterportalapi/v1/region/identitycenterportalapi_region.py
huaweicloudsdkidentitycenterportalapi-3.1.184.dist-info/METADATA
huaweicloudsdkidentitycenterportalapi-3.1.184.dist-info/WHEEL
huaweicloudsdkidentitycenterportalapi-3.1.184.dist-info/licenses/LICENSE
huaweicloudsdkidentitycenterportalapi-3.1.184.dist-info/RECORD
